autocrosswalk/__init__.py
autocrosswalk/main.py
autocrosswalk/tools.py
autocrosswalk/data/__init__.py
autocrosswalk/data/example_data.parquet
autocrosswalk/data/missing_data.parquet
autocrosswalk/data/missing_data_nomissing.parquet
autocrosswalk/matching/__init__.py
autocrosswalk/matching/context_matching.py
autocrosswalk/matching/numeric_matching.py
autocrosswalk/matching/text_matching.py
autocrosswalk-0.0.24.dist-info/LICENSE
autocrosswalk-0.0.24.dist-info/METADATA
autocrosswalk-0.0.24.dist-info/WHEEL
autocrosswalk-0.0.24.dist-info/top_level.txt
autocrosswalk-0.0.24.dist-info/RECORD
