Metadata-Version: 2.1
Name: autocrosswalk
Version: 0.0.24
Summary: Automatic Crosswalk
Home-page: https://github.com/muhlbach/autocrosswalk
Author: Nicolaj Søndergaard Mühlbach
Author-email: n.muhlbach@gmail.com
License: MIT License
Keywords: natural language processing,deep learning,machine learning
Platform: UNKNOWN
Classifier: Programming Language :: Python :: 3
Classifier: License :: OSI Approved :: MIT License
Classifier: Operating System :: OS Independent
Requires-Python: >=3.6
License-File: LICENSE
Requires-Dist: bodyguard (>=0.0.41)
Requires-Dist: econnlp (>=0.0.7)
